[
  {
    "date": "2025-09-11",
    "code": "1519",
    "name": "華城",
    "market": "TWSE",
    "foreign_ratio": 0.0,
    "trust_ratio": 0.0,
    "dealer_ratio": 0.0,
    "three_inst_ratio": 0.0,
    "three_inst_ratio_change_20": 0.0
  },
  {
    "date": "2025-09-12",
    "code": "1519",
    "name": "華城",
    "market": "TWSE",
    "foreign_ratio": 0.0,
    "trust_ratio": 0.0,
    "dealer_ratio": 0.0,
    "three_inst_ratio": 0.0,
    "three_inst_ratio_change_20": 0.0
  },
  {
    "date": "2025-09-15",
    "code": "1519",
    "name": "華城",
    "market": "TWSE",
    "foreign_ratio": 0.0,
    "trust_ratio": 0.0,
    "dealer_ratio": 0.0,
    "three_inst_ratio": 0.0,
    "three_inst_ratio_change_20": 0.0
  },
  {
    "date": "2025-09-16",
    "code": "1519",
    "name": "華城",
    "market": "TWSE",
    "foreign_ratio": 0.0,
    "trust_ratio": 0.0,
    "dealer_ratio": 0.0,
    "three_inst_ratio": 0.0,
    "three_inst_ratio_change_20": 0.0
  },
  {
    "date": "2025-09-17",
    "code": "1519",
    "name": "華城",
    "market": "TWSE",
    "foreign_ratio": 0.0,
    "trust_ratio": 0.0,
    "dealer_ratio": 0.0,
    "three_inst_ratio": 0.0,
    "three_inst_ratio_change_20": 0.0
  },
  {
    "date": "2025-09-18",
    "code": "1519",
    "name": "華城",
    "market": "TWSE",
    "foreign_ratio": 0.0,
    "trust_ratio": 0.0,
    "dealer_ratio": 0.0,
    "three_inst_ratio": 0.0,
    "three_inst_ratio_change_20": 0.0
  },
  {
    "date": "2025-09-19",
    "code": "1519",
    "name": "華城",
    "market": "TWSE",
    "foreign_ratio": 0.0,
    "trust_ratio": 0.0,
    "dealer_ratio": 0.0,
    "three_inst_ratio": 0.0,
    "three_inst_ratio_change_20": 0.0
  },
  {
    "date": "2025-09-22",
    "code": "1519",
    "name": "華城",
    "market": "TWSE",
    "foreign_ratio": 0.0,
    "trust_ratio": 0.0,
    "dealer_ratio": 0.0,
    "three_inst_ratio": 0.0,
    "three_inst_ratio_change_20": 0.0
  },
  {
    "date": "2025-09-23",
    "code": "1519",
    "name": "華城",
    "market": "TWSE",
    "foreign_ratio": 0.0,
    "trust_ratio": 0.0,
    "dealer_ratio": 0.0,
    "three_inst_ratio": 0.0,
    "three_inst_ratio_change_20": 0.0
  },
  {
    "date": "2025-09-24",
    "code": "1519",
    "name": "華城",
    "market": "TWSE",
    "foreign_ratio": 0.0,
    "trust_ratio": 0.0,
    "dealer_ratio": 0.0,
    "three_inst_ratio": 0.0,
    "three_inst_ratio_change_20": 0.0
  },
  {
    "date": "2025-09-25",
    "code": "1519",
    "name": "華城",
    "market": "TWSE",
    "foreign_ratio": 0.0,
    "trust_ratio": 0.0,
    "dealer_ratio": 0.0,
    "three_inst_ratio": 0.0,
    "three_inst_ratio_change_20": 0.0
  },
  {
    "date": "2025-09-26",
    "code": "1519",
    "name": "華城",
    "market": "TWSE",
    "foreign_ratio": 0.0,
    "trust_ratio": 0.0,
    "dealer_ratio": 0.0,
    "three_inst_ratio": 0.0,
    "three_inst_ratio_change_20": 0.0
  },
  {
    "date": "2025-09-30",
    "code": "1519",
    "name": "華城",
    "market": "TWSE",
    "foreign_ratio": 0.0,
    "trust_ratio": 0.0,
    "dealer_ratio": 0.0,
    "three_inst_ratio": 0.0,
    "three_inst_ratio_change_20": 0.0
  },
  {
    "date": "2025-10-01",
    "code": "1519",
    "name": "華城",
    "market": "TWSE",
    "foreign_ratio": 0.0,
    "trust_ratio": 0.0,
    "dealer_ratio": 0.0,
    "three_inst_ratio": 0.0,
    "three_inst_ratio_change_20": 0.0
  },
  {
    "date": "2025-10-02",
    "code": "1519",
    "name": "華城",
    "market": "TWSE",
    "foreign_ratio": 0.0,
    "trust_ratio": 0.0,
    "dealer_ratio": 0.0,
    "three_inst_ratio": 0.0,
    "three_inst_ratio_change_20": 0.0
  },
  {
    "date": "2025-10-03",
    "code": "1519",
    "name": "華城",
    "market": "TWSE",
    "foreign_ratio": 0.0,
    "trust_ratio": 0.0,
    "dealer_ratio": 0.0,
    "three_inst_ratio": 0.0,
    "three_inst_ratio_change_20": 0.0
  },
  {
    "date": "2025-10-07",
    "code": "1519",
    "name": "華城",
    "market": "TWSE",
    "foreign_ratio": 18.12,
    "trust_ratio": 0.5754419853329251,
    "dealer_ratio": 0.0,
    "three_inst_ratio": 18.695441985332927,
    "three_inst_ratio_change_20": 0.0
  },
  {
    "date": "2025-10-08",
    "code": "1519",
    "name": "華城",
    "market": "TWSE",
    "foreign_ratio": 18.09,
    "trust_ratio": 0.577639016312113,
    "dealer_ratio": 0.0,
    "three_inst_ratio": 18.667639016312112,
    "three_inst_ratio_change_20": 0.0
  },
  {
    "date": "2025-10-09",
    "code": "1519",
    "name": "華城",
    "market": "TWSE",
    "foreign_ratio": 18.02,
    "trust_ratio": 0.5905239381974046,
    "dealer_ratio": 0.0,
    "three_inst_ratio": 18.610523938197403,
    "three_inst_ratio_change_20": 0.0
  },
  {
    "date": "2025-10-13",
    "code": "1519",
    "name": "華城",
    "market": "TWSE",
    "foreign_ratio": 18.05,
    "trust_ratio": 0.5907961927567852,
    "dealer_ratio": 0.0,
    "three_inst_ratio": 18.640796192756785,
    "three_inst_ratio_change_20": 0.0
  },
  {
    "date": "2025-10-14",
    "code": "1519",
    "name": "華城",
    "market": "TWSE",
    "foreign_ratio": 18.09,
    "trust_ratio": 0.5956198470838581,
    "dealer_ratio": 0.0,
    "three_inst_ratio": 18.685619847083856,
    "three_inst_ratio_change_20": 18.685619847083856
  },
  {
    "date": "2025-10-15",
    "code": "1519",
    "name": "華城",
    "market": "TWSE",
    "foreign_ratio": 18.15,
    "trust_ratio": 0.5965695722909997,
    "dealer_ratio": 0.0,
    "three_inst_ratio": 18.746569572290998,
    "three_inst_ratio_change_20": 18.746569572290998
  },
  {
    "date": "2025-10-16",
    "code": "1519",
    "name": "華城",
    "market": "TWSE",
    "foreign_ratio": 18.31,
    "trust_ratio": 0.5972027224290942,
    "dealer_ratio": 0.0,
    "three_inst_ratio": 18.907202722429094,
    "three_inst_ratio_change_20": 18.907202722429094
  },
  {
    "date": "2025-10-17",
    "code": "1519",
    "name": "華城",
    "market": "TWSE",
    "foreign_ratio": 18.23,
    "trust_ratio": 0.603534223810039,
    "dealer_ratio": 0.0,
    "three_inst_ratio": 18.83353422381004,
    "three_inst_ratio_change_20": 18.83353422381004
  },
  {
    "date": "2025-10-20",
    "code": "1519",
    "name": "華城",
    "market": "TWSE",
    "foreign_ratio": 18.22,
    "trust_ratio": 0.6366790003891467,
    "dealer_ratio": 0.0,
    "three_inst_ratio": 18.856679000389146,
    "three_inst_ratio_change_20": 18.856679000389146
  },
  {
    "date": "2025-10-21",
    "code": "1519",
    "name": "華城",
    "market": "TWSE",
    "foreign_ratio": 18.45,
    "trust_ratio": 0.6826222738596963,
    "dealer_ratio": 0.0,
    "three_inst_ratio": 19.132622273859695,
    "three_inst_ratio_change_20": 19.132622273859695
  },
  {
    "date": "2025-10-22",
    "code": "1519",
    "name": "華城",
    "market": "TWSE",
    "foreign_ratio": 18.54,
    "trust_ratio": 0.7237770328358373,
    "dealer_ratio": 0.0,
    "three_inst_ratio": 19.263777032835836,
    "three_inst_ratio_change_20": 19.263777032835836
  },
  {
    "date": "2025-10-23",
    "code": "1519",
    "name": "華城",
    "market": "TWSE",
    "foreign_ratio": 18.45,
    "trust_ratio": 0.7655649419500729,
    "dealer_ratio": 0.0,
    "three_inst_ratio": 19.21556494195007,
    "three_inst_ratio_change_20": 19.21556494195007
  },
  {
    "date": "2025-10-27",
    "code": "1519",
    "name": "華城",
    "market": "TWSE",
    "foreign_ratio": 18.58,
    "trust_ratio": 0.8262257903806285,
    "dealer_ratio": 0.0,
    "three_inst_ratio": 19.406225790380628,
    "three_inst_ratio_change_20": 19.406225790380628
  },
  {
    "date": "2025-10-28",
    "code": "1519",
    "name": "華城",
    "market": "TWSE",
    "foreign_ratio": 19.04,
    "trust_ratio": 0.8293915410711009,
    "dealer_ratio": 0.0,
    "three_inst_ratio": 19.8693915410711,
    "three_inst_ratio_change_20": 19.8693915410711
  },
  {
    "date": "2025-10-29",
    "code": "1519",
    "name": "華城",
    "market": "TWSE",
    "foreign_ratio": 18.83,
    "trust_ratio": 0.8293915410711009,
    "dealer_ratio": 0.0,
    "three_inst_ratio": 19.6593915410711,
    "three_inst_ratio_change_20": 19.6593915410711
  },
  {
    "date": "2025-10-30",
    "code": "1519",
    "name": "華城",
    "market": "TWSE",
    "foreign_ratio": 19.96,
    "trust_ratio": 0.8863750534996038,
    "dealer_ratio": 0.0,
    "three_inst_ratio": 20.846375053499603,
    "three_inst_ratio_change_20": 20.846375053499603
  },
  {
    "date": "2025-10-31",
    "code": "1519",
    "name": "華城",
    "market": "TWSE",
    "foreign_ratio": 20.77,
    "trust_ratio": 0.9097617201503995,
    "dealer_ratio": 0.0,
    "three_inst_ratio": 21.6797617201504,
    "three_inst_ratio_change_20": 21.6797617201504
  },
  {
    "date": "2025-11-03",
    "code": "1519",
    "name": "華城",
    "market": "TWSE",
    "foreign_ratio": 21.26,
    "trust_ratio": 1.0643136688592614,
    "dealer_ratio": 0.0,
    "three_inst_ratio": 22.32431366885926,
    "three_inst_ratio_change_20": 22.32431366885926
  },
  {
    "date": "2025-11-04",
    "code": "1519",
    "name": "華城",
    "market": "TWSE",
    "foreign_ratio": 21.49,
    "trust_ratio": 1.1098605903433638,
    "dealer_ratio": 0.0,
    "three_inst_ratio": 22.59986059034336,
    "three_inst_ratio_change_20": 22.59986059034336
  },
  {
    "date": "2025-11-05",
    "code": "1519",
    "name": "華城",
    "market": "TWSE",
    "foreign_ratio": 21.39,
    "trust_ratio": 1.1202537498601846,
    "dealer_ratio": 0.0,
    "three_inst_ratio": 22.510253749860183,
    "three_inst_ratio_change_20": 22.510253749860183
  },
  {
    "date": "2025-11-06",
    "code": "1519",
    "name": "華城",
    "market": "TWSE",
    "foreign_ratio": 21.37,
    "trust_ratio": 1.1535818234042707,
    "dealer_ratio": 0.0,
    "three_inst_ratio": 22.52358182340427,
    "three_inst_ratio_change_20": 3.828139838071344
  },
  {
    "date": "2025-11-07",
    "code": "1519",
    "name": "華城",
    "market": "TWSE",
    "foreign_ratio": 21.21,
    "trust_ratio": 1.1536286765144896,
    "dealer_ratio": 0.0,
    "three_inst_ratio": 22.36362867651449,
    "three_inst_ratio_change_20": 3.695989660202379
  },
  {
    "date": "2025-11-10",
    "code": "1519",
    "name": "華城",
    "market": "TWSE",
    "foreign_ratio": 21.3,
    "trust_ratio": 1.1852662391898636,
    "dealer_ratio": 0.0,
    "three_inst_ratio": 22.485266239189865,
    "three_inst_ratio_change_20": 3.8747423009924624
  },
  {
    "date": "2025-11-11",
    "code": "1519",
    "name": "華城",
    "market": "TWSE",
    "foreign_ratio": 21.38,
    "trust_ratio": 1.18508800742599,
    "dealer_ratio": 0.0,
    "three_inst_ratio": 22.565088007425988,
    "three_inst_ratio_change_20": 3.9242918146692034
  },
  {
    "date": "2025-11-12",
    "code": "1519",
    "name": "華城",
    "market": "TWSE",
    "foreign_ratio": 21.39,
    "trust_ratio": 1.2194164581882656,
    "dealer_ratio": 0.0,
    "three_inst_ratio": 22.609416458188267,
    "three_inst_ratio_change_20": 3.923796611104411
  },
  {
    "date": "2025-11-13",
    "code": "1519",
    "name": "華城",
    "market": "TWSE",
    "foreign_ratio": 21.43,
    "trust_ratio": 1.2194164581882656,
    "dealer_ratio": 0.0,
    "three_inst_ratio": 22.649416458188266,
    "three_inst_ratio_change_20": 3.9028468858972687
  },
  {
    "date": "2025-11-14",
    "code": "1519",
    "name": "華城",
    "market": "TWSE",
    "foreign_ratio": 21.48,
    "trust_ratio": 1.219238542999461,
    "dealer_ratio": 0.0,
    "three_inst_ratio": 22.69923854299946,
    "three_inst_ratio_change_20": 3.7920358205703657
  },
  {
    "date": "2025-11-17",
    "code": "1519",
    "name": "華城",
    "market": "TWSE",
    "foreign_ratio": 21.54,
    "trust_ratio": 1.219238542999461,
    "dealer_ratio": 0.0,
    "three_inst_ratio": 22.75923854299946,
    "three_inst_ratio_change_20": 3.9257043191894176
  },
  {
    "date": "2025-11-18",
    "code": "1519",
    "name": "華城",
    "market": "TWSE",
    "foreign_ratio": 21.54,
    "trust_ratio": 1.2186053928613665,
    "dealer_ratio": 0.0,
    "three_inst_ratio": 22.758605392861366,
    "three_inst_ratio_change_20": 3.9019263924722196
  },
  {
    "date": "2025-11-19",
    "code": "1519",
    "name": "華城",
    "market": "TWSE",
    "foreign_ratio": 21.53,
    "trust_ratio": 1.217599000716865,
    "dealer_ratio": 0.0,
    "three_inst_ratio": 22.747599000716868,
    "three_inst_ratio_change_20": 3.614976726857172
  },
  {
    "date": "2025-11-20",
    "code": "1519",
    "name": "華城",
    "market": "TWSE",
    "foreign_ratio": 21.19,
    "trust_ratio": 1.2687939380078395,
    "dealer_ratio": 0.0,
    "three_inst_ratio": 22.45879393800784,
    "three_inst_ratio_change_20": 3.195016905172004
  },
  {
    "date": "2025-11-21",
    "code": "1519",
    "name": "華城",
    "market": "TWSE",
    "foreign_ratio": 20.96,
    "trust_ratio": 1.3223828159709488,
    "dealer_ratio": 0.0,
    "three_inst_ratio": 22.282382815970948,
    "three_inst_ratio_change_20": 3.0668178740208774
  },
  {
    "date": "2025-11-24",
    "code": "1519",
    "name": "華城",
    "market": "TWSE",
    "foreign_ratio": 21.06,
    "trust_ratio": 1.3423232464200963,
    "dealer_ratio": 0.0,
    "three_inst_ratio": 22.402323246420096,
    "three_inst_ratio_change_20": 2.996097456039468
  },
  {
    "date": "2025-11-25",
    "code": "1519",
    "name": "華城",
    "market": "TWSE",
    "foreign_ratio": 20.87,
    "trust_ratio": 1.3427601200153814,
    "dealer_ratio": 0.0,
    "three_inst_ratio": 22.212760120015382,
    "three_inst_ratio_change_20": 2.3433685789442826
  },
  {
    "date": "2025-11-26",
    "code": "1519",
    "name": "華城",
    "market": "TWSE",
    "foreign_ratio": 20.81,
    "trust_ratio": 1.3763170773343887,
    "dealer_ratio": 0.0,
    "three_inst_ratio": 22.186317077334387,
    "three_inst_ratio_change_20": 2.5269255362632883
  },
  {
    "date": "2025-11-27",
    "code": "1519",
    "name": "華城",
    "market": "TWSE",
    "foreign_ratio": 20.82,
    "trust_ratio": 1.4092934359767635,
    "dealer_ratio": 0.0,
    "three_inst_ratio": 22.229293435976764,
    "three_inst_ratio_change_20": 1.3829183824771611
  },
  {
    "date": "2025-11-28",
    "code": "1519",
    "name": "華城",
    "market": "TWSE",
    "foreign_ratio": 20.19,
    "trust_ratio": 1.4149917872196138,
    "dealer_ratio": 0.0,
    "three_inst_ratio": 21.604991787219614,
    "three_inst_ratio_change_20": -0.07476993293078493
  },
  {
    "date": "2025-12-01",
    "code": "1519",
    "name": "華城",
    "market": "TWSE",
    "foreign_ratio": 20.4,
    "trust_ratio": 1.4444332686410069,
    "dealer_ratio": 0.0,
    "three_inst_ratio": 21.844433268641005,
    "three_inst_ratio_change_20": -0.4798804002182564
  },
  {
    "date": "2025-12-02",
    "code": "1519",
    "name": "華城",
    "market": "TWSE",
    "foreign_ratio": 20.18,
    "trust_ratio": 1.488081056285895,
    "dealer_ratio": 0.0,
    "three_inst_ratio": 21.668081056285896,
    "three_inst_ratio_change_20": -0.9317795340574655
  },
  {
    "date": "2025-12-03",
    "code": "1519",
    "name": "華城",
    "market": "TWSE",
    "foreign_ratio": 20.12,
    "trust_ratio": 1.4879031410970904,
    "dealer_ratio": 0.0,
    "three_inst_ratio": 21.60790314109709,
    "three_inst_ratio_change_20": -0.9023506087630935
  },
  {
    "date": "2025-12-04",
    "code": "1519",
    "name": "華城",
    "market": "TWSE",
    "foreign_ratio": 20.17,
    "trust_ratio": 1.510063395930397,
    "dealer_ratio": 0.0,
    "three_inst_ratio": 21.6800633959304,
    "three_inst_ratio_change_20": -0.843518427473871
  },
  {
    "date": "2025-12-05",
    "code": "1519",
    "name": "華城",
    "market": "TWSE",
    "foreign_ratio": 20.19,
    "trust_ratio": 1.5154451721042002,
    "dealer_ratio": 0.0,
    "three_inst_ratio": 21.705445172104202,
    "three_inst_ratio_change_20": -0.6581835044102888
  },
  {
    "date": "2025-12-08",
    "code": "1519",
    "name": "華城",
    "market": "TWSE",
    "foreign_ratio": 20.04,
    "trust_ratio": 1.568902671413655,
    "dealer_ratio": 0.0,
    "three_inst_ratio": 21.608902671413652,
    "three_inst_ratio_change_20": -0.8763635677762132
  },
  {
    "date": "2025-12-09",
    "code": "1519",
    "name": "華城",
    "market": "TWSE",
    "foreign_ratio": 20.19,
    "trust_ratio": 1.596721705606181,
    "dealer_ratio": 0.0,
    "three_inst_ratio": 21.786721705606183,
    "three_inst_ratio_change_20": -0.7783663018198048
  },
  {
    "date": "2025-12-10",
    "code": "1519",
    "name": "華城",
    "market": "TWSE",
    "foreign_ratio": 20.35,
    "trust_ratio": 1.719018137104889,
    "dealer_ratio": 0.0,
    "three_inst_ratio": 22.06901813710489,
    "three_inst_ratio_change_20": -0.5403983210833765
  },
  {
    "date": "2025-12-11",
    "code": "1519",
    "name": "華城",
    "market": "TWSE",
    "foreign_ratio": 20.06,
    "trust_ratio": 1.7515845310328473,
    "dealer_ratio": 0.0,
    "three_inst_ratio": 21.811584531032846,
    "three_inst_ratio_change_20": -0.8378319271554204
  },
  {
    "date": "2025-12-12",
    "code": "1519",
    "name": "華城",
    "market": "TWSE",
    "foreign_ratio": 20.59,
    "trust_ratio": 1.7591427608063501,
    "dealer_ratio": 0.0,
    "three_inst_ratio": 22.34914276080635,
    "three_inst_ratio_change_20": -0.3500957821931081
  },
  {
    "date": "2025-12-15",
    "code": "1519",
    "name": "華城",
    "market": "TWSE",
    "foreign_ratio": 20.67,
    "trust_ratio": 1.8714860721342128,
    "dealer_ratio": 0.0,
    "three_inst_ratio": 22.541486072134216,
    "three_inst_ratio_change_20": -0.21775247086524274
  },
  {
    "date": "2025-12-16",
    "code": "1519",
    "name": "華城",
    "market": "TWSE",
    "foreign_ratio": 20.44,
    "trust_ratio": 1.9362782252158348,
    "dealer_ratio": 0.0,
    "three_inst_ratio": 22.376278225215835,
    "three_inst_ratio_change_20": -0.3823271676455313
  },
  {
    "date": "2025-12-17",
    "code": "1519",
    "name": "華城",
    "market": "TWSE",
    "foreign_ratio": 20.04,
    "trust_ratio": 1.9465491867560036,
    "dealer_ratio": 0.0,
    "three_inst_ratio": 21.986549186756,
    "three_inst_ratio_change_20": -0.7610498139608666
  },
  {
    "date": "2025-12-18",
    "code": "1519",
    "name": "華城",
    "market": "TWSE",
    "foreign_ratio": 19.97,
    "trust_ratio": 1.9718751922797824,
    "dealer_ratio": 0.0,
    "three_inst_ratio": 21.94187519227978,
    "three_inst_ratio_change_20": -0.5169187457280593
  },
  {
    "date": "2025-12-19",
    "code": "1519",
    "name": "華城",
    "market": "TWSE",
    "foreign_ratio": 19.97,
    "trust_ratio": 1.9927691468369004,
    "dealer_ratio": 0.0,
    "three_inst_ratio": 21.962769146836898,
    "three_inst_ratio_change_20": -0.31961366913404987
  },
  {
    "date": "2025-12-22",
    "code": "1519",
    "name": "華城",
    "market": "TWSE",
    "foreign_ratio": 20.08,
    "trust_ratio": 2.0166528363461,
    "dealer_ratio": 0.0,
    "three_inst_ratio": 22.0966528363461,
    "three_inst_ratio_change_20": -0.3056704100739971
  },
  {
    "date": "2025-12-23",
    "code": "1519",
    "name": "華城",
    "market": "TWSE",
    "foreign_ratio": 20.14,
    "trust_ratio": 2.0527423942174856,
    "dealer_ratio": 0.0,
    "three_inst_ratio": 22.192742394217486,
    "three_inst_ratio_change_20": -0.020017725797895736
  },
  {
    "date": "2025-12-24",
    "code": "1519",
    "name": "華城",
    "market": "TWSE",
    "foreign_ratio": 20.05,
    "trust_ratio": 2.049260068457966,
    "dealer_ratio": 0.0,
    "three_inst_ratio": 22.099260068457966,
    "three_inst_ratio_change_20": -0.0870570088764211
  },
  {
    "date": "2025-12-25",
    "code": "1519",
    "name": "華城",
    "market": "TWSE",
    "foreign_ratio": 0.0,
    "trust_ratio": 0.0,
    "dealer_ratio": 0.0,
    "three_inst_ratio": 0.0,
    "three_inst_ratio_change_20": -22.229293435976764
  },
  {
    "date": "2025-12-26",
    "code": "1519",
    "name": "華城",
    "market": "TWSE",
    "foreign_ratio": 20.1,
    "trust_ratio": 2.0745860739817448,
    "dealer_ratio": 0.0,
    "three_inst_ratio": 22.174586073981747,
    "three_inst_ratio_change_20": 0.5695942867621326
  },
  {
    "date": "2025-12-29",
    "code": "1519",
    "name": "華城",
    "market": "TWSE",
    "foreign_ratio": 20.04,
    "trust_ratio": 2.068571147669847,
    "dealer_ratio": 0.0,
    "three_inst_ratio": 22.108571147669846,
    "three_inst_ratio_change_20": 0.26413787902884067
  },
  {
    "date": "2025-12-30",
    "code": "1519",
    "name": "華城",
    "market": "TWSE",
    "foreign_ratio": 20.09,
    "trust_ratio": 2.0185187298030645,
    "dealer_ratio": 0.0,
    "three_inst_ratio": 22.108518729803066,
    "three_inst_ratio_change_20": 0.4404376735171702
  },
  {
    "date": "2025-12-31",
    "code": "1519",
    "name": "華城",
    "market": "TWSE",
    "foreign_ratio": 20.01,
    "trust_ratio": 2.0128200619851455,
    "dealer_ratio": 0.0,
    "three_inst_ratio": 22.022820061985147,
    "three_inst_ratio_change_20": 0.4149169208880572
  },
  {
    "date": "2026-01-02",
    "code": "1519",
    "name": "華城",
    "market": "TWSE",
    "foreign_ratio": 19.87,
    "trust_ratio": 1.918480691409068,
    "dealer_ratio": 0.0,
    "three_inst_ratio": 21.78848069140907,
    "three_inst_ratio_change_20": 0.10841729547867018
  },
  {
    "date": "2026-01-05",
    "code": "1519",
    "name": "華城",
    "market": "TWSE",
    "foreign_ratio": 19.89,
    "trust_ratio": 1.910162048319714,
    "dealer_ratio": 0.0,
    "three_inst_ratio": 21.800162048319713,
    "three_inst_ratio_change_20": 0.09471687621551084
  },
  {
    "date": "2026-01-06",
    "code": "1519",
    "name": "華城",
    "market": "TWSE",
    "foreign_ratio": 19.87,
    "trust_ratio": 1.771291329081038,
    "dealer_ratio": 0.0,
    "three_inst_ratio": 21.64129132908104,
    "three_inst_ratio_change_20": 0.03238865766738641
  },
  {
    "date": "2026-01-07",
    "code": "1519",
    "name": "華城",
    "market": "TWSE",
    "foreign_ratio": 19.8,
    "trust_ratio": 1.794967661920012,
    "dealer_ratio": 0.0,
    "three_inst_ratio": 21.594967661920013,
    "three_inst_ratio_change_20": -0.19175404368617066
  },
  {
    "date": "2026-01-08",
    "code": "1519",
    "name": "華城",
    "market": "TWSE",
    "foreign_ratio": 19.43,
    "trust_ratio": 1.7985227999454123,
    "dealer_ratio": 0.0,
    "three_inst_ratio": 21.228522799945413,
    "three_inst_ratio_change_20": -0.8404953371594779
  },
  {
    "date": "2026-01-09",
    "code": "1519",
    "name": "華城",
    "market": "TWSE",
    "foreign_ratio": 19.79,
    "trust_ratio": 1.8872008585617175,
    "dealer_ratio": 0.0,
    "three_inst_ratio": 21.677200858561715,
    "three_inst_ratio_change_20": -0.13438367247113092
  },
  {
    "date": "2026-01-12",
    "code": "1519",
    "name": "華城",
    "market": "TWSE",
    "foreign_ratio": 20.47,
    "trust_ratio": 1.921252622713646,
    "dealer_ratio": 0.0,
    "three_inst_ratio": 22.391252622713644,
    "three_inst_ratio_change_20": 0.042109861907292157
  },
  {
    "date": "2026-01-13",
    "code": "1519",
    "name": "華城",
    "market": "TWSE",
    "foreign_ratio": 20.52,
    "trust_ratio": 2.012885276449369,
    "dealer_ratio": 0.0,
    "three_inst_ratio": 22.53288527644937,
    "three_inst_ratio_change_20": -0.008600795684845508
  },
  {
    "date": "2026-01-14",
    "code": "1519",
    "name": "華城",
    "market": "TWSE",
    "foreign_ratio": 20.99,
    "trust_ratio": 2.0484854092640075,
    "dealer_ratio": 0.0,
    "three_inst_ratio": 23.038485409264005,
    "three_inst_ratio_change_20": 0.6622071840481709
  },
  {
    "date": "2026-01-15",
    "code": "1519",
    "name": "華城",
    "market": "TWSE",
    "foreign_ratio": 21.42,
    "trust_ratio": 2.1501794518441897,
    "dealer_ratio": 0.0,
    "three_inst_ratio": 23.57017945184419,
    "three_inst_ratio_change_20": 1.583630265088189
  },
  {
    "date": "2026-01-16",
    "code": "1519",
    "name": "華城",
    "market": "TWSE",
    "foreign_ratio": 21.39,
    "trust_ratio": 2.351551270389793,
    "dealer_ratio": 0.0,
    "three_inst_ratio": 23.74155127038979,
    "three_inst_ratio_change_20": 1.7996760781100107
  },
  {
    "date": "2026-01-19",
    "code": "1519",
    "name": "華城",
    "market": "TWSE",
    "foreign_ratio": 21.06,
    "trust_ratio": 2.353663459250476,
    "dealer_ratio": 0.0,
    "three_inst_ratio": 23.413663459250476,
    "three_inst_ratio_change_20": 1.4508943124135776
  },
  {
    "date": "2026-01-20",
    "code": "1519",
    "name": "華城",
    "market": "TWSE",
    "foreign_ratio": 21.43,
    "trust_ratio": 2.373834989500028,
    "dealer_ratio": 0.0,
    "three_inst_ratio": 23.80383498950003,
    "three_inst_ratio_change_20": 1.70718215315393
  }
]